README.md
setup.cfg
setup.py
wwpdb/__init__.py
wwpdb.apps.wf_engine.egg-info/PKG-INFO
wwpdb.apps.wf_engine.egg-info/SOURCES.txt
wwpdb.apps.wf_engine.egg-info/dependency_links.txt
wwpdb.apps.wf_engine.egg-info/not-zip-safe
wwpdb.apps.wf_engine.egg-info/requires.txt
wwpdb.apps.wf_engine.egg-info/top_level.txt
wwpdb/apps/__init__.py
wwpdb/apps/wf_engine/__init__.py
wwpdb/apps/wf_engine/engine/CommandLineArgs.py
wwpdb/apps/wf_engine/engine/EngineUtils.py
wwpdb/apps/wf_engine/engine/ExternalTask.py
wwpdb/apps/wf_engine/engine/InterpretDataObject.py
wwpdb/apps/wf_engine/engine/ProcessManager.py
wwpdb/apps/wf_engine/engine/ServerMonitor.py
wwpdb/apps/wf_engine/engine/SwitchTask.py
wwpdb/apps/wf_engine/engine/WFEapplications.py
wwpdb/apps/wf_engine/engine/WorkflowManager.py
wwpdb/apps/wf_engine/engine/WorkflowSession.py
wwpdb/apps/wf_engine/engine/__init__.py
wwpdb/apps/wf_engine/engine/autorun.py
wwpdb/apps/wf_engine/engine/dbAPI.py
wwpdb/apps/wf_engine/engine/mainEngine.py
wwpdb/apps/wf_engine/reader/TaskComparitor.py
wwpdb/apps/wf_engine/reader/TaskParameter.py
wwpdb/apps/wf_engine/reader/__init__.py
wwpdb/apps/wf_engine/reader/dataReference.py
wwpdb/apps/wf_engine/reader/metaDataObject.py
wwpdb/apps/wf_engine/reader/parseTimeDelta.py
wwpdb/apps/wf_engine/reader/parseXML.py
wwpdb/apps/wf_engine/reader/taskReference.py
wwpdb/apps/wf_engine/wf_engine_utils/__init__.py
wwpdb/apps/wf_engine/wf_engine_utils/process/ProcessUtils.py
wwpdb/apps/wf_engine/wf_engine_utils/process/__init__.py
wwpdb/apps/wf_engine/wf_engine_utils/run/MyLogger.py
wwpdb/apps/wf_engine/wf_engine_utils/run/WFEngineRunner.py
wwpdb/apps/wf_engine/wf_engine_utils/run/WFEngineRunnerExec.py
wwpdb/apps/wf_engine/wf_engine_utils/run/__init__.py
wwpdb/apps/wf_engine/wf_engine_utils/tasks/WFTaskRequest.py
wwpdb/apps/wf_engine/wf_engine_utils/tasks/WFTaskRequestExec.py
wwpdb/apps/wf_engine/wf_engine_utils/tasks/__init__.py
wwpdb/apps/wf_engine/wf_engine_utils/test/test-bmrb-codes.ids
wwpdb/apps/wf_engine/wf_engine_utils/test/test-emdb-codes.ids
wwpdb/apps/wf_engine/wf_engine_utils/test/test-pdb-codes.ids
wwpdb/apps/wf_engine/wf_engine_utils/time/TimeStamp.py
wwpdb/apps/wf_engine/wf_engine_utils/time/__init__.py