Metadata-Version: 2.4
Name: wwpdb.apps.wf_engine
Version: 0.20
Summary: wwPDB workflow engine utils
Home-page: https://github.com/rcsb/py-wwpdb_apps_wf_engine_utils
Author: Ezra Peisach
Author-email: ezra.peisach@rcsb.org
License: Apache 2.0
Classifier: Development Status :: 3 - Alpha
Classifier: Intended Audience :: Developers
Classifier: Natural Language :: English
Classifier: License :: OSI Approved :: Apache Software License
Classifier: Programming Language :: Python
Classifier: Programming Language :: Python :: 2.7
Classifier: Programming Language :: Python :: 3
Classifier: Programming Language :: Python :: 3.6
Classifier: Programming Language :: Python :: 3.7
Requires-Dist: psutil
Requires-Dist: python-dateutil
Requires-Dist: mmcif.utils
Requires-Dist: wwpdb.utils.db
Requires-Dist: wwpdb.utils.config
Requires-Dist: wwpdb.utils.wf>=0.5
Requires-Dist: wwpdb.utils.detach
Requires-Dist: wwpdb.io>=0.36
Requires-Dist: tabulate
Requires-Dist: future
Provides-Extra: dev
Requires-Dist: check-manifest; extra == "dev"
Provides-Extra: test
Requires-Dist: coverage; extra == "test"
Dynamic: author
Dynamic: author-email
Dynamic: classifier
Dynamic: description
Dynamic: home-page
Dynamic: license
Dynamic: provides-extra
Dynamic: requires-dist
Dynamic: summary
